fasttrack_client/__init__.py
fasttrack_client/client.py
fasttrack_client/common.py
fasttrack_client/constants.py
fasttrack_client/exceptions.py
fasttrack_client/meta.py
fasttrack_client-1.0.4.dist-info/DESCRIPTION.rst
fasttrack_client-1.0.4.dist-info/METADATA
fasttrack_client-1.0.4.dist-info/RECORD
fasttrack_client-1.0.4.dist-info/WHEEL
fasttrack_client-1.0.4.dist-info/metadata.json
fasttrack_client-1.0.4.dist-info/top_level.txt
